curvlinops/__init__.py
curvlinops/_torch_base.py
curvlinops/ekfac.py
curvlinops/fisher.py
curvlinops/ggn.py
curvlinops/gradient_moments.py
curvlinops/hessian.py
curvlinops/inverse.py
curvlinops/jacobian.py
curvlinops/kfac.py
curvlinops/kfac_utils.py
curvlinops/sampling.py
curvlinops/submatrix.py
curvlinops/utils.py
curvlinops/diagonal/__init__.py
curvlinops/diagonal/epperly2024xtrace.py
curvlinops/diagonal/hutchinson.py
curvlinops/examples/__init__.py
curvlinops/examples/functorch.py
curvlinops/experimental/__init__.py
curvlinops/experimental/activation_hessian.py
curvlinops/norm/__init__.py
curvlinops/norm/hutchinson.py
curvlinops/papyan2020traces/__init__.py
curvlinops/papyan2020traces/spectrum.py
curvlinops/trace/__init__.py
curvlinops/trace/epperly2024xtrace.py
curvlinops/trace/hutchinson.py
curvlinops/trace/meyer2020hutch.py
curvlinops_for_pytorch-3.0.1.dist-info/licenses/LICENSE
curvlinops_for_pytorch-3.0.1.dist-info/METADATA
curvlinops_for_pytorch-3.0.1.dist-info/WHEEL
curvlinops_for_pytorch-3.0.1.dist-info/top_level.txt
curvlinops_for_pytorch-3.0.1.dist-info/RECORD
