Metadata-Version: 2.4
Name: curvlinops-for-pytorch
Version: 3.0.1
Summary: scipy Linear operators for curvature matrices in PyTorch
Author: Felix Dangel, Runa Eschenhagen, Lukas Tatzel, Andres Fernandez
License: MIT
Project-URL: Repository, https://github.com/f-dangel/curvlinops
Classifier: Development Status :: 4 - Beta
Classifier: License :: OSI Approved :: MIT License
Classifier: Operating System :: OS Independent
Classifier: Programming Language :: Python :: 3.10
Classifier: Programming Language :: Python :: 3.11
Classifier: Programming Language :: Python :: 3.12
Requires-Python: >=3.10
License-File: LICENSE
Requires-Dist: backpack-for-pytorch>=1.6.0
Requires-Dist: torch>=2.0
Requires-Dist: scipy>=1.0.0
Requires-Dist: numpy>=1.21.0
Requires-Dist: tqdm>=4.0.0
Requires-Dist: einops>=0.3.0
Requires-Dist: einconv>=0.1.0
Requires-Dist: linear_operator>=0.2.0
Requires-Dist: opt-einsum>=3.4.0
Provides-Extra: test
Requires-Dist: matplotlib; extra == "test"
Requires-Dist: tueplots; extra == "test"
Requires-Dist: coveralls; extra == "test"
Requires-Dist: pytest; extra == "test"
Requires-Dist: pytest-cov; extra == "test"
Requires-Dist: pytest-optional-tests==0.1.1; extra == "test"
Provides-Extra: lint
Requires-Dist: ruff; extra == "lint"
Requires-Dist: darglint; extra == "lint"
Requires-Dist: pydocstyle; extra == "lint"
Provides-Extra: docs
Requires-Dist: memory_profiler; extra == "docs"
Requires-Dist: transformers; extra == "docs"
Requires-Dist: tiktoken; extra == "docs"
Requires-Dist: datasets; extra == "docs"
Requires-Dist: matplotlib; extra == "docs"
Requires-Dist: sphinx-gallery; extra == "docs"
Requires-Dist: sphinx-rtd-theme; extra == "docs"
Requires-Dist: tueplots; extra == "docs"
Dynamic: license-file
